[{"id":"autos-y-motos-1","file":"/stickers/autos-y-motos/1.webp","sku":"000384","stock":50},{"id":"autos-y-motos-2","file":"/stickers/autos-y-motos/2.webp","sku":"000385","stock":50},{"id":"autos-y-motos-3","file":"/stickers/autos-y-motos/3.webp","sku":"000386","stock":50},{"id":"autos-y-motos-4","file":"/stickers/autos-y-motos/4.webp","sku":"000387","stock":50},{"id":"autos-y-motos-5","file":"/stickers/autos-y-motos/5.webp","sku":"000388","stock":50},{"id":"autos-y-motos-6","file":"/stickers/autos-y-motos/6.webp","sku":"000389","stock":50},{"id":"autos-y-motos-7","file":"/stickers/autos-y-motos/7.webp","sku":"000390","stock":50},{"id":"autos-y-motos-8","file":"/stickers/autos-y-motos/8.webp","sku":"000391","stock":50},{"id":"autos-y-motos-9","file":"/stickers/autos-y-motos/9.webp","sku":"000392","stock":50},{"id":"autos-y-motos-10","file":"/stickers/autos-y-motos/10.webp","sku":"000393","stock":50},{"id":"autos-y-motos-11","file":"/stickers/autos-y-motos/11.webp","sku":"000394","stock":50},{"id":"autos-y-motos-12","file":"/stickers/autos-y-motos/12.webp","sku":"000395","stock":50},{"id":"autos-y-motos-13","file":"/stickers/autos-y-motos/13.webp","sku":"000396","stock":50},{"id":"autos-y-motos-14","file":"/stickers/autos-y-motos/14.webp","sku":"000397","stock":50},{"id":"autos-y-motos-15","file":"/stickers/autos-y-motos/15.webp","sku":"000398","stock":50},{"id":"autos-y-motos-16","file":"/stickers/autos-y-motos/16.webp","sku":"000399","stock":50},{"id":"autos-y-motos-17","file":"/stickers/autos-y-motos/17.webp","sku":"000400","stock":50},{"id":"autos-y-motos-18","file":"/stickers/autos-y-motos/18.webp","sku":"000401","stock":50},{"id":"autos-y-motos-19","file":"/stickers/autos-y-motos/19.webp","sku":"000402","stock":50},{"id":"autos-y-motos-20","file":"/stickers/autos-y-motos/20.webp","sku":"000403","stock":50},{"id":"autos-y-motos-21","file":"/stickers/autos-y-motos/21.webp","sku":"000404","stock":50},{"id":"autos-y-motos-22","file":"/stickers/autos-y-motos/22.webp","sku":"000405","stock":50},{"id":"autos-y-motos-23","file":"/stickers/autos-y-motos/23.webp","sku":"000406","stock":50},{"id":"autos-y-motos-24","file":"/stickers/autos-y-motos/24.webp","sku":"000407","stock":50},{"id":"autos-y-motos-25","file":"/stickers/autos-y-motos/25.webp","sku":"000408","stock":50},{"id":"autos-y-motos-26","file":"/stickers/autos-y-motos/26.webp","sku":"000409","stock":50},{"id":"autos-y-motos-27","file":"/stickers/autos-y-motos/27.webp","sku":"000410","stock":50},{"id":"autos-y-motos-28","file":"/stickers/autos-y-motos/28.webp","sku":"000411","stock":50},{"id":"autos-y-motos-29","file":"/stickers/autos-y-motos/29.webp","sku":"000412","stock":50},{"id":"autos-y-motos-30","file":"/stickers/autos-y-motos/30.webp","sku":"000413","stock":50},{"id":"autos-y-motos-31","file":"/stickers/autos-y-motos/31.webp","sku":"000414","stock":50},{"id":"autos-y-motos-32","file":"/stickers/autos-y-motos/32.webp","sku":"000415","stock":50},{"id":"autos-y-motos-33","file":"/stickers/autos-y-motos/33.webp","sku":"000416","stock":50},{"id":"autos-y-motos-34","file":"/stickers/autos-y-motos/34.webp","sku":"000417","stock":50},{"id":"autos-y-motos-35","file":"/stickers/autos-y-motos/35.webp","sku":"000418","stock":50},{"id":"autos-y-motos-36","file":"/stickers/autos-y-motos/36.webp","sku":"000419","stock":50},{"id":"autos-y-motos-37","file":"/stickers/autos-y-motos/37.webp","sku":"000420","stock":50},{"id":"autos-y-motos-38","file":"/stickers/autos-y-motos/38.webp","sku":"000421","stock":50},{"id":"autos-y-motos-39","file":"/stickers/autos-y-motos/39.webp","sku":"000422","stock":50},{"id":"autos-y-motos-40","file":"/stickers/autos-y-motos/40.webp","sku":"000423","stock":50},{"id":"autos-y-motos-41","file":"/stickers/autos-y-motos/41.webp","sku":"000424","stock":50},{"id":"autos-y-motos-42","file":"/stickers/autos-y-motos/42.webp","sku":"000425","stock":50},{"id":"autos-y-motos-43","file":"/stickers/autos-y-motos/43.webp","sku":"000426","stock":50},{"id":"autos-y-motos-44","file":"/stickers/autos-y-motos/44.webp","sku":"000427","stock":50},{"id":"autos-y-motos-45","file":"/stickers/autos-y-motos/45.webp","sku":"000428","stock":50},{"id":"autos-y-motos-46","file":"/stickers/autos-y-motos/46.webp","sku":"000429","stock":50},{"id":"autos-y-motos-47","file":"/stickers/autos-y-motos/47.webp","sku":"000430","stock":50},{"id":"autos-y-motos-48","file":"/stickers/autos-y-motos/48.webp","sku":"000431","stock":50},{"id":"autos-y-motos-49","file":"/stickers/autos-y-motos/49.webp","sku":"000432","stock":50},{"id":"autos-y-motos-50","file":"/stickers/autos-y-motos/50.webp","sku":"000433","stock":50},{"id":"autos-y-motos-51","file":"/stickers/autos-y-motos/51.webp","sku":"000434","stock":50},{"id":"autos-y-motos-52","file":"/stickers/autos-y-motos/52.webp","sku":"000435","stock":50},{"id":"autos-y-motos-53","file":"/stickers/autos-y-motos/53.webp","sku":"000436","stock":50},{"id":"autos-y-motos-54","file":"/stickers/autos-y-motos/54.webp","sku":"000437","stock":50},{"id":"autos-y-motos-55","file":"/stickers/autos-y-motos/55.webp","sku":"000438","stock":50},{"id":"autos-y-motos-56","file":"/stickers/autos-y-motos/56.webp","sku":"000439","stock":50},{"id":"autos-y-motos-57","file":"/stickers/autos-y-motos/57.webp","sku":"000440","stock":50},{"id":"autos-y-motos-58","file":"/stickers/autos-y-motos/58.webp","sku":"000441","stock":50},{"id":"autos-y-motos-59","file":"/stickers/autos-y-motos/59.webp","sku":"000442","stock":50},{"id":"autos-y-motos-60","file":"/stickers/autos-y-motos/60.webp","sku":"000443","stock":50},{"id":"autos-y-motos-61","file":"/stickers/autos-y-motos/61.webp","sku":"000444","stock":50},{"id":"autos-y-motos-62","file":"/stickers/autos-y-motos/62.webp","sku":"000445","stock":50},{"id":"autos-y-motos-63","file":"/stickers/autos-y-motos/63.webp","sku":"000446","stock":50},{"id":"autos-y-motos-64","file":"/stickers/autos-y-motos/64.webp","sku":"000447","stock":50},{"id":"autos-y-motos-65","file":"/stickers/autos-y-motos/65.webp","sku":"000448","stock":50},{"id":"autos-y-motos-66","file":"/stickers/autos-y-motos/66.webp","sku":"000449","stock":50},{"id":"autos-y-motos-67","file":"/stickers/autos-y-motos/67.webp","sku":"000450","stock":50},{"id":"autos-y-motos-68","file":"/stickers/autos-y-motos/68.webp","sku":"000451","stock":50},{"id":"autos-y-motos-69","file":"/stickers/autos-y-motos/69.webp","sku":"000452","stock":50},{"id":"autos-y-motos-70","file":"/stickers/autos-y-motos/70.webp","sku":"000453","stock":50},{"id":"autos-y-motos-71","file":"/stickers/autos-y-motos/71.webp","sku":"000454","stock":50},{"id":"autos-y-motos-72","file":"/stickers/autos-y-motos/72.webp","sku":"000455","stock":50},{"id":"autos-y-motos-73","file":"/stickers/autos-y-motos/73.webp","sku":"000456","stock":50},{"id":"autos-y-motos-74","file":"/stickers/autos-y-motos/74.webp","sku":"000457","stock":50},{"id":"autos-y-motos-75","file":"/stickers/autos-y-motos/75.webp","sku":"000458","stock":50},{"id":"autos-y-motos-76","file":"/stickers/autos-y-motos/76.webp","sku":"000459","stock":50},{"id":"autos-y-motos-77","file":"/stickers/autos-y-motos/77.webp","sku":"000460","stock":50},{"id":"autos-y-motos-78","file":"/stickers/autos-y-motos/78.webp","sku":"000461","stock":50},{"id":"autos-y-motos-79","file":"/stickers/autos-y-motos/79.webp","sku":"000462","stock":50},{"id":"autos-y-motos-80","file":"/stickers/autos-y-motos/80.webp","sku":"000463","stock":50},{"id":"autos-y-motos-81","file":"/stickers/autos-y-motos/81.webp","sku":"000464","stock":50},{"id":"autos-y-motos-82","file":"/stickers/autos-y-motos/82.webp","sku":"000465","stock":50},{"id":"autos-y-motos-83","file":"/stickers/autos-y-motos/83.webp","sku":"000466","stock":50},{"id":"autos-y-motos-84","file":"/stickers/autos-y-motos/84.webp","sku":"000467","stock":50},{"id":"autos-y-motos-85","file":"/stickers/autos-y-motos/85.webp","sku":"000468","stock":50},{"id":"autos-y-motos-86","file":"/stickers/autos-y-motos/86.webp","sku":"000469","stock":50},{"id":"autos-y-motos-87","file":"/stickers/autos-y-motos/87.webp","sku":"000470","stock":50},{"id":"autos-y-motos-88","file":"/stickers/autos-y-motos/88.webp","sku":"000471","stock":50},{"id":"autos-y-motos-89","file":"/stickers/autos-y-motos/89.webp","sku":"000472","stock":50},{"id":"autos-y-motos-90","file":"/stickers/autos-y-motos/90.webp","sku":"000473","stock":50},{"id":"autos-y-motos-91","file":"/stickers/autos-y-motos/91.webp","sku":"000474","stock":50},{"id":"autos-y-motos-92","file":"/stickers/autos-y-motos/92.webp","sku":"000475","stock":50},{"id":"autos-y-motos-93","file":"/stickers/autos-y-motos/93.webp","sku":"000476","stock":50},{"id":"autos-y-motos-94","file":"/stickers/autos-y-motos/94.webp","sku":"000477","stock":50},{"id":"autos-y-motos-95","file":"/stickers/autos-y-motos/95.webp","sku":"000478","stock":50},{"id":"autos-y-motos-96","file":"/stickers/autos-y-motos/96.webp","sku":"000479","stock":50},{"id":"autos-y-motos-97","file":"/stickers/autos-y-motos/97.webp","sku":"000480","stock":50},{"id":"autos-y-motos-98","file":"/stickers/autos-y-motos/98.webp","sku":"000481","stock":50},{"id":"autos-y-motos-99","file":"/stickers/autos-y-motos/99.webp","sku":"000482","stock":50},{"id":"autos-y-motos-100","file":"/stickers/autos-y-motos/100.webp","sku":"000483","stock":50},{"id":"autos-y-motos-101","file":"/stickers/autos-y-motos/101.webp","sku":"000484","stock":50},{"id":"autos-y-motos-102","file":"/stickers/autos-y-motos/102.webp","sku":"000485","stock":50},{"id":"autos-y-motos-103","file":"/stickers/autos-y-motos/103.webp","sku":"000486","stock":50},{"id":"autos-y-motos-104","file":"/stickers/autos-y-motos/104.webp","sku":"000487","stock":50},{"id":"autos-y-motos-105","file":"/stickers/autos-y-motos/105.webp","sku":"000488","stock":50},{"id":"autos-y-motos-106","file":"/stickers/autos-y-motos/106.webp","sku":"000489","stock":50},{"id":"autos-y-motos-107","file":"/stickers/autos-y-motos/107.webp","sku":"000490","stock":50},{"id":"autos-y-motos-108","file":"/stickers/autos-y-motos/108.webp","sku":"000491","stock":50},{"id":"autos-y-motos-109","file":"/stickers/autos-y-motos/109.webp","sku":"000492","stock":50},{"id":"autos-y-motos-110","file":"/stickers/autos-y-motos/110.webp","sku":"000493","stock":50},{"id":"autos-y-motos-111","file":"/stickers/autos-y-motos/111.webp","sku":"000494","stock":50},{"id":"autos-y-motos-112","file":"/stickers/autos-y-motos/112.webp","sku":"000495","stock":50},{"id":"autos-y-motos-113","file":"/stickers/autos-y-motos/113.webp","sku":"000496","stock":50},{"id":"autos-y-motos-114","file":"/stickers/autos-y-motos/114.webp","sku":"000497","stock":50},{"id":"autos-y-motos-115","file":"/stickers/autos-y-motos/115.webp","sku":"000498","stock":50},{"id":"autos-y-motos-116","file":"/stickers/autos-y-motos/116.webp","sku":"000499","stock":50},{"id":"autos-y-motos-117","file":"/stickers/autos-y-motos/117.webp","sku":"000500","stock":50},{"id":"autos-y-motos-118","file":"/stickers/autos-y-motos/118.webp","sku":"000501","stock":50},{"id":"autos-y-motos-119","file":"/stickers/autos-y-motos/119.webp","sku":"000502","stock":50},{"id":"autos-y-motos-120","file":"/stickers/autos-y-motos/120.webp","sku":"000503","stock":50},{"id":"autos-y-motos-121","file":"/stickers/autos-y-motos/121.webp","sku":"000504","stock":50},{"id":"autos-y-motos-122","file":"/stickers/autos-y-motos/122.webp","sku":"000505","stock":50},{"id":"autos-y-motos-123","file":"/stickers/autos-y-motos/123.webp","sku":"000506","stock":50},{"id":"autos-y-motos-124","file":"/stickers/autos-y-motos/124.webp","sku":"000507","stock":50},{"id":"autos-y-motos-125","file":"/stickers/autos-y-motos/125.webp","sku":"000508","stock":50},{"id":"autos-y-motos-126","file":"/stickers/autos-y-motos/126.webp","sku":"000509","stock":50},{"id":"autos-y-motos-127","file":"/stickers/autos-y-motos/127.webp","sku":"000510","stock":50}]