[{"slug":"anime","count":254,"cover":"/stickers/anime/1.webp"},{"slug":"argentina","count":126,"cover":"/stickers/argentina/1.webp"},{"slug":"autos-y-motos","count":127,"cover":"/stickers/autos-y-motos/1.webp"},{"slug":"bob-esponja","count":182,"cover":"/stickers/bob-esponja/1.webp"},{"slug":"buenas-vibras","count":78,"cover":"/stickers/buenas-vibras/1.webp"},{"slug":"calcos-especiales","count":108,"cover":"/stickers/calcos-especiales/1.webp"},{"slug":"campeones","count":179,"cover":"/stickers/campeones/1.webp"},{"slug":"cats","count":166,"cover":"/stickers/cats/1.webp"},{"slug":"ciencia","count":52,"cover":"/stickers/ciencia/1.webp"},{"slug":"cute","count":163,"cover":"/stickers/cute/1.webp"},{"slug":"deportes","count":176,"cover":"/stickers/deportes/1.webp"},{"slug":"digimon","count":49,"cover":"/stickers/digimon/1.webp"},{"slug":"disney","count":396,"cover":"/stickers/disney/1.webp"},{"slug":"dragon-ball","count":103,"cover":"/stickers/dragon-ball/1.webp"},{"slug":"futbol","count":169,"cover":"/stickers/futbol/1.webp"},{"slug":"gamer","count":166,"cover":"/stickers/gamer/1.webp"},{"slug":"girl-power","count":95,"cover":"/stickers/girl-power/1.webp"},{"slug":"halloween","count":47,"cover":"/stickers/halloween/1.webp"},{"slug":"harry-potter","count":102,"cover":"/stickers/harry-potter/1.webp"},{"slug":"homedeco","count":68,"cover":"/stickers/homedeco/1.webp"},{"slug":"infantil","count":388,"cover":"/stickers/infantil/1.webp"},{"slug":"los-simpsons","count":149,"cover":"/stickers/los-simpsons/1.webp"},{"slug":"marcas","count":78,"cover":"/stickers/marcas/1.webp"},{"slug":"memes","count":210,"cover":"/stickers/memes/1.webp"},{"slug":"musica","count":133,"cover":"/stickers/musica/1.webp"},{"slug":"naruto","count":48,"cover":"/stickers/naruto/1.webp"},{"slug":"nba","count":65,"cover":"/stickers/nba/1.webp"},{"slug":"pokemon","count":81,"cover":"/stickers/pokemon/1.webp"},{"slug":"pride","count":37,"cover":"/stickers/pride/1.webp"},{"slug":"rap-reggaeton","count":109,"cover":"/stickers/rap-reggaeton/1.webp"},{"slug":"rick-and-morty","count":56,"cover":"/stickers/rick-and-morty/1.webp"},{"slug":"series-peliculas","count":184,"cover":"/stickers/series-peliculas/1.webp"},{"slug":"space","count":52,"cover":"/stickers/space/1.webp"},{"slug":"star-wars","count":76,"cover":"/stickers/star-wars/1.webp"},{"slug":"superheroes","count":135,"cover":"/stickers/superheroes/1.webp"},{"slug":"viajes","count":151,"cover":"/stickers/viajes/1.webp"},{"slug":"weed-creepy","count":328,"cover":"/stickers/weed-creepy/1.webp"}]