[{"id":"space-1","file":"/stickers/space/1.webp"},{"id":"space-2","file":"/stickers/space/2.webp"},{"id":"space-3","file":"/stickers/space/3.webp"},{"id":"space-4","file":"/stickers/space/4.webp"},{"id":"space-5","file":"/stickers/space/5.webp"},{"id":"space-6","file":"/stickers/space/6.webp"},{"id":"space-7","file":"/stickers/space/7.webp"},{"id":"space-8","file":"/stickers/space/8.webp"},{"id":"space-9","file":"/stickers/space/9.webp"},{"id":"space-10","file":"/stickers/space/10.webp"},{"id":"space-11","file":"/stickers/space/11.webp"},{"id":"space-12","file":"/stickers/space/12.webp"},{"id":"space-13","file":"/stickers/space/13.webp"},{"id":"space-14","file":"/stickers/space/14.webp"},{"id":"space-15","file":"/stickers/space/15.webp"},{"id":"space-16","file":"/stickers/space/16.webp"},{"id":"space-17","file":"/stickers/space/17.webp"},{"id":"space-18","file":"/stickers/space/18.webp"},{"id":"space-19","file":"/stickers/space/19.webp"},{"id":"space-20","file":"/stickers/space/20.webp"},{"id":"space-21","file":"/stickers/space/21.webp"},{"id":"space-22","file":"/stickers/space/22.webp"},{"id":"space-23","file":"/stickers/space/23.webp"},{"id":"space-24","file":"/stickers/space/24.webp"},{"id":"space-25","file":"/stickers/space/25.webp"},{"id":"space-26","file":"/stickers/space/26.webp"},{"id":"space-27","file":"/stickers/space/27.webp"},{"id":"space-28","file":"/stickers/space/28.webp"},{"id":"space-29","file":"/stickers/space/29.webp"},{"id":"space-30","file":"/stickers/space/30.webp"},{"id":"space-31","file":"/stickers/space/31.webp"},{"id":"space-32","file":"/stickers/space/32.webp"},{"id":"space-33","file":"/stickers/space/33.webp"},{"id":"space-34","file":"/stickers/space/34.webp"},{"id":"space-35","file":"/stickers/space/35.webp"},{"id":"space-36","file":"/stickers/space/36.webp"},{"id":"space-37","file":"/stickers/space/37.webp"},{"id":"space-38","file":"/stickers/space/38.webp"},{"id":"space-39","file":"/stickers/space/39.webp"},{"id":"space-40","file":"/stickers/space/40.webp"},{"id":"space-41","file":"/stickers/space/41.webp"},{"id":"space-43","file":"/stickers/space/43.webp"},{"id":"space-44","file":"/stickers/space/44.webp"},{"id":"space-45","file":"/stickers/space/45.webp"},{"id":"space-46","file":"/stickers/space/46.webp"},{"id":"space-47","file":"/stickers/space/47.webp"},{"id":"space-48","file":"/stickers/space/48.webp"},{"id":"space-49","file":"/stickers/space/49.webp"},{"id":"space-50","file":"/stickers/space/50.webp"},{"id":"space-51","file":"/stickers/space/51.webp"},{"id":"space-52","file":"/stickers/space/52.webp"},{"id":"space-53","file":"/stickers/space/53.webp"}]